pd_db_wrangler/__init__.py
pd_db_wrangler/pd_db_wrangler.py
pd_db_wrangler/tester.py
pd_db_wrangler-0.28.0.dist-info/AUTHORS.rst
pd_db_wrangler-0.28.0.dist-info/LICENSE
pd_db_wrangler-0.28.0.dist-info/METADATA
pd_db_wrangler-0.28.0.dist-info/WHEEL
pd_db_wrangler-0.28.0.dist-info/entry_points.txt
pd_db_wrangler-0.28.0.dist-info/top_level.txt
pd_db_wrangler-0.28.0.dist-info/RECORD
