Metadata-Version: 2.1
Name: pd-db-wrangler
Version: 0.28.0
Summary: Pandas database helper library
Home-page: https://github.com/kellerjustin/pd_db_wrangler
Author: Justin Keller
Author-email: kellerjustin@protonmail.com
License: MIT license
Keywords: pd_db_wrangler
Classifier: Development Status :: 2 - Pre-Alpha
Classifier: Intended Audience :: Developers
Classifier: License :: OSI Approved :: MIT License
Classifier: Natural Language :: English
Classifier: Programming Language :: Python :: 3
Classifier: Programming Language :: Python :: 3.5
Classifier: Programming Language :: Python :: 3.6
Classifier: Programming Language :: Python :: 3.7
Classifier: Programming Language :: Python :: 3.8
Requires-Python: >=3.5
License-File: LICENSE
License-File: AUTHORS.rst
Requires-Dist: pandas
Requires-Dist: sqlalchemy
Requires-Dist: psycopg2
